neurostore/__init__.py
neurostore/chat.py
neurostore/embedding_models.py
neurostore/utils.py
neurostore-1.0.0.dist-info/LICENSE
neurostore-1.0.0.dist-info/METADATA
neurostore-1.0.0.dist-info/WHEEL
neurostore-1.0.0.dist-info/top_level.txt
neurostore-1.0.0.dist-info/RECORD
