Metadata-Version: 2.1
Name: neurostore
Version: 1.0.0
Summary: A package for storing and managing LLM queries.
Maintainer-email: Kunal Kapur <kunalkapur888@gmail.com>
License: == Neurostore License (MIT) ==
Project-URL: Homepage, https://github.com/kunal-kapur/neurostore
Keywords: openAI,milvus,vector database
Requires-Python: >=3.11
License-File: LICENSE
Requires-Dist: pymilvus
Requires-Dist: pymilvus[model]
Requires-Dist: openai
Requires-Dist: keybert
Requires-Dist: numpy<2
Provides-Extra: dev
Requires-Dist: black>24.1.0; extra == "dev"
Requires-Dist: pytest>=8.0.0; extra == "dev"
Requires-Dist: flake8; extra == "dev"
Requires-Dist: mypy>1.10.0; extra == "dev"
Requires-Dist: build; extra == "dev"
Requires-Dist: twine>=5.1.1; extra == "dev"
